smooch/__init__.py
smooch/api_client.py
smooch/configuration.py
smooch/rest.py
smooch/apis/__init__.py
smooch/apis/app_api.py
smooch/apis/app_user_api.py
smooch/apis/attachments_api.py
smooch/apis/conversation_api.py
smooch/apis/deployment_api.py
smooch/apis/integration_api.py
smooch/apis/menu_api.py
smooch/apis/notification_api.py
smooch/apis/service_account_api.py
smooch/apis/template_api.py
smooch/apis/webhook_api.py
smooch/models/__init__.py
smooch/models/action.py
smooch/models/activity_response.py
smooch/models/app.py
smooch/models/app_create.py
smooch/models/app_response.py
smooch/models/app_settings.py
smooch/models/app_update.py
smooch/models/app_user.py
smooch/models/app_user_business_systems_response.py
smooch/models/app_user_channels_response.py
smooch/models/app_user_link.py
smooch/models/app_user_merge.py
smooch/models/app_user_pre_create.py
smooch/models/app_user_response.py
smooch/models/app_user_update.py
smooch/models/attachment_remove.py
smooch/models/attachment_response.py
smooch/models/auth_code_response.py
smooch/models/author.py
smooch/models/business_system_item.py
smooch/models/channel_entity_item.py
smooch/models/client.py
smooch/models/client_info.py
smooch/models/confirmation.py
smooch/models/conversation.py
smooch/models/conversation_activity.py
smooch/models/coordinates.py
smooch/models/deployment.py
smooch/models/deployment_activate_phone_number.py
smooch/models/deployment_confirm_code.py
smooch/models/deployment_create.py
smooch/models/deployment_response.py
smooch/models/destination.py
smooch/models/display_settings.py
smooch/models/enums.py
smooch/models/field.py
smooch/models/field_post.py
smooch/models/get_integration_profile_response.py
smooch/models/get_messages_response.py
smooch/models/get_sdk_ids_response.py
smooch/models/integration.py
smooch/models/integration_create.py
smooch/models/integration_profile_update.py
smooch/models/integration_response.py
smooch/models/integration_update.py
smooch/models/jwt_response.py
smooch-5.34.0.dist-info/LICENSE
smooch-5.34.0.dist-info/METADATA
smooch-5.34.0.dist-info/WHEEL
smooch-5.34.0.dist-info/top_level.txt
smooch-5.34.0.dist-info/RECORD
