Metadata-Version: 2.1
Name: smooch
Version: 5.34.0
Summary: Smooch
Home-page: UNKNOWN
Author: UNKNOWN
Author-email: UNKNOWN
License: UNKNOWN
Keywords: Swagger,Smooch
Platform: UNKNOWN
Requires-Dist: urllib3 (>=1.15)
Requires-Dist: six (>=1.10)
Requires-Dist: certifi
Requires-Dist: python-dateutil
